randpercent
