Metadata-Version: 1.1
Name: randpercent
Version: 0.0.3
Summary: A library to generate booleans with a given percentage.
Home-page: UNKNOWN
Author: Eric Sivak
Author-email: eric.sivak05@googlemail.com
License: MIT
Keywords: random,booleans
Platform: UNKNOWN
Classifier: Development Status :: 5 - Production/Stable
Classifier: Intended Audience :: Education
Classifier: Operating System :: Microsoft :: Windows :: Windows 10
Classifier: License :: OSI Approved :: MIT License
Classifier: Programming Language :: Python :: 3
